debseed/__init__.py
debseed/__main__.py
debseed/_version.py
debseed/check.py
debseed/debian.py
debseed/download.py
debseed/generate.py
debseed/listiso.py
debseed/publish.py
debseed/settings.py
debseed/update.py
debseed/utils.py
debseed/assets/debian-cd-signing.gpg
debseed/assets/late-command.sh
debseed/assets/preseed.cfg.j2
debseed/assets/late-command-assets/target/etc/skel/.bashrc
debseed/assets/late-command-assets/target/etc/ssh/sshd_config.j2
debseed/assets/late-command-assets/target/etc/sudoers.d/forward-git-user
debseed/assets/late-command-assets/target/etc/sudoers.d/forward-ssh-agent
debseed/assets/late-command-assets/target/etc/sudoers.d/nopasswd-user.j2
debseed/assets/late-command-assets/target/etc/systemd/system/debseed-firstboot.service
debseed/assets/late-command-assets/target/etc/systemd/timesyncd.conf.d/ntp-servers.conf.j2
debseed/assets/late-command-assets/target/etc/vim/vimrc.local
debseed/assets/late-command-assets/target/root/.bashrc
debseed/assets/late-command-assets/target/var/local/debseed-firstboot/destruct
debseed/assets/late-command-assets/target/var/local/debseed-firstboot/main
debseed/assets/late-command-assets/target/var/local/debseed-firstboot/required.top
debseed/assets/late-command-assets/target/var/local/debseed-firstboot/parts.d/srv-group.j2
debseed/external/__init__.py
debseed/external/interface.py
debseed/external/vmware.py
debseed-0.1.3.dist-info/LICENSE.txt
debseed-0.1.3.dist-info/METADATA
debseed-0.1.3.dist-info/WHEEL
debseed-0.1.3.dist-info/entry_points.txt
debseed-0.1.3.dist-info/top_level.txt
debseed-0.1.3.dist-info/RECORD
