Metadata-Version: 2.1
Name: debseed
Version: 0.1.3
Summary: Create ISO images to automate Debian installations, by appending a preseed file to Debian official images.
Author-email: Ipamo <dev@ipamo.net>
Project-URL: Homepage, https://gitlab.com/ipamo/debseed
Project-URL: Bug Tracker, https://gitlab.com/ipamo/debseed/issues
Keywords: adaptation,iso,installation,debian,netinst,preseed
Requires-Python: >=3.7.3
License-File: LICENSE.txt
Requires-Dist: jinja2 (>=3.1.2)
Requires-Dist: tabulate (>=0.9.0)
Provides-Extra: all
Requires-Dist: jinja2 (>=3.1.2) ; extra == 'all'
Requires-Dist: tabulate (>=0.9.0) ; extra == 'all'
Requires-Dist: pyvmomi (>=7.0.3) ; extra == 'all'
Provides-Extra: vmware
Requires-Dist: jinja2 (>=3.1.2) ; extra == 'vmware'
Requires-Dist: tabulate (>=0.9.0) ; extra == 'vmware'
Requires-Dist: pyvmomi (>=7.0.3) ; extra == 'vmware'
